{
    "courseName": "PSY202H1S",
    "courseType": "S",
    "meetings": [
        {
            "meetingName": "LEC5101",
            "meetingType": "LEC",
            "instructors": [
                "M Metz"
            ],
            "detail": [
                {
                    "meetingDay": 1,
                    "meetingStartTime": "18:00",
                    "meetingEndTime": "20:00",
                    "meetingScheduleId": "152142",
                    "assignedRoom1": null,
                    "assignedRoom2": null
                }
            ],
            "meetingId": "101937",
            "sectionNumber": "5101",
            "subtitle": "",
            "cancel": "",
            "waitlist": "Y",
            "online": "",
            "enrollmentCapacity": "200",
            "actualEnrolment": "0",
            "actualWaitlist": "0",
            "enrollmentIndicator": "P",
            "meetingStatusNotes": null,
            "enrollmentControls": [
                {
                    "postId": "90",
                    "postCode": "ASMAJ1160",
                    "postName": "MA PSYCHOLOGY",
                    "subjectId": "1",
                    "subjectCode": "*",
                    "subjectName": "",
                    "designationId": "1",
                    "designationCode": "*",
                    "designationName": "",
                    "yearOfStudy": "*",
                    "typeOfProgramId": "1",
                    "typeOfProgramCode": "*",
                    "typeOfProgramName": "All Types",
                    "primaryOrgId": "1",
                    "primaryOrgCode": "*",
                    "primaryOrgName": "",
                    "secondaryOrgId": "1",
                    "secondaryOrgCode": "*",
                    "secondaryOrgName": "",
                    "assocOrgId": "1",
                    "assocOrgCode": "*",
                    "assocOrgName": "",
                    "adminOrgId": "1",
                    "adminOrgCode": "*",
                    "adminOrgName": ""
                },
                {
                    "postId": "193",
                    "postCode": "ASMIN1160",
                    "postName": "MI PSYCHOLOGY",
                    "subjectId": "1",
                    "subjectCode": "*",
                    "subjectName": "",
                    "designationId": "1",
                    "designationCode": "*",
                    "designationName": "",
                    "yearOfStudy": "*",
                    "typeOfProgramId": "1",
                    "typeOfProgramCode": "*",
                    "typeOfProgramName": "All Types",
                    "primaryOrgId": "1",
                    "primaryOrgCode": "*",
                    "primaryOrgName": "",
                    "secondaryOrgId": "1",
                    "secondaryOrgCode": "*",
                    "secondaryOrgName": "",
                    "assocOrgId": "1",
                    "assocOrgCode": "*",
                    "assocOrgName": "",
                    "adminOrgId": "1",
                    "adminOrgCode": "*",
                    "adminOrgName": ""
                },
                {
                    "postId": "287",
                    "postCode": "ASSPE1160",
                    "postName": "SP PSYCHOLOGY",
                    "subjectId": "1",
                    "subjectCode": "*",
                    "subjectName": "",
                    "designationId": "1",
                    "designationCode": "*",
                    "designationName": "",
                    "yearOfStudy": "*",
                    "typeOfProgramId": "1",
                    "typeOfProgramCode": "*",
                    "typeOfProgramName": "All Types",
                    "primaryOrgId": "1",
                    "primaryOrgCode": "*",
                    "primaryOrgName": "",
                    "secondaryOrgId": "1",
                    "secondaryOrgCode": "*",
                    "secondaryOrgName": "",
                    "assocOrgId": "1",
                    "assocOrgCode": "*",
                    "assocOrgName": "",
                    "adminOrgId": "1",
                    "adminOrgCode": "*",
                    "adminOrgName": ""
                },
                {
                    "postId": "353",
                    "postCode": "ASSPE1958",
                    "postName": "SP PSYCHOLOGY RESEARCH(THESIS)",
                    "subjectId": "1",
                    "subjectCode": "*",
                    "subjectName": "",
                    "designationId": "1",
                    "designationCode": "*",
                    "designationName": "",
                    "yearOfStudy": "*",
                    "typeOfProgramId": "1",
                    "typeOfProgramCode": "*",
                    "typeOfProgramName": "All Types",
                    "primaryOrgId": "1",
                    "primaryOrgCode": "*",
                    "primaryOrgName": "",
                    "secondaryOrgId": "1",
                    "secondaryOrgCode": "*",
                    "secondaryOrgName": "",
                    "assocOrgId": "1",
                    "assocOrgCode": "*",
                    "assocOrgName": "",
                    "adminOrgId": "1",
                    "adminOrgCode": "*",
                    "adminOrgName": ""
                }
            ]
        },
        {
            "meetingName": "TUT0101",
            "meetingType": "TUT",
            "instructors": [],
            "detail": [
                {
                    "meetingDay": 2,
                    "meetingStartTime": "09:00",
                    "meetingEndTime": "10:00",
                    "meetingScheduleId": "158849",
                    "assignedRoom1": null,
                    "assignedRoom2": ""
                }
            ],
            "meetingId": "101938",
            "sectionNumber": "0101",
            "subtitle": "",
            "cancel": "",
            "waitlist": "N",
            "online": "",
            "enrollmentCapacity": "20",
            "actualEnrolment": "0",
            "actualWaitlist": "0",
            "enrollmentIndicator": null,
            "meetingStatusNotes": null,
            "enrollmentControls": []
        },
        {
            "meetingName": "TUT0201",
            "meetingType": "TUT",
            "instructors": [],
            "detail": [
                {
                    "meetingDay": 2,
                    "meetingStartTime": "10:00",
                    "meetingEndTime": "11:00",
                    "meetingScheduleId": "158851",
                    "assignedRoom1": null,
                    "assignedRoom2": ""
                }
            ],
            "meetingId": "101939",
            "sectionNumber": "0201",
            "subtitle": "",
            "cancel": "",
            "waitlist": "N",
            "online": "",
            "enrollmentCapacity": "20",
            "actualEnrolment": "0",
            "actualWaitlist": "0",
            "enrollmentIndicator": null,
            "meetingStatusNotes": null,
            "enrollmentControls": []
        },
        {
            "meetingName": "TUT0301",
            "meetingType": "TUT",
            "instructors": [],
            "detail": [
                {
                    "meetingDay": 3,
                    "meetingStartTime": "10:00",
                    "meetingEndTime": "11:00",
                    "meetingScheduleId": "158852",
                    "assignedRoom1": null,
                    "assignedRoom2": ""
                }
            ],
            "meetingId": "101940",
            "sectionNumber": "0301",
            "subtitle": "",
            "cancel": "",
            "waitlist": "N",
            "online": "",
            "enrollmentCapacity": "20",
            "actualEnrolment": "0",
            "actualWaitlist": "0",
            "enrollmentIndicator": null,
            "meetingStatusNotes": null,
            "enrollmentControls": []
        },
        {
            "meetingName": "TUT0401",
            "meetingType": "TUT",
            "instructors": [],
            "detail": [
                {
                    "meetingDay": 3,
                    "meetingStartTime": "11:00",
                    "meetingEndTime": "12:00",
                    "meetingScheduleId": "158853",
                    "assignedRoom1": null,
                    "assignedRoom2": ""
                }
            ],
            "meetingId": "101941",
            "sectionNumber": "0401",
            "subtitle": "",
            "cancel": "",
            "waitlist": "N",
            "online": "",
            "enrollmentCapacity": "20",
            "actualEnrolment": "0",
            "actualWaitlist": "0",
            "enrollmentIndicator": null,
            "meetingStatusNotes": null,
            "enrollmentControls": []
        },
        {
            "meetingName": "TUT0501",
            "meetingType": "TUT",
            "instructors": [],
            "detail": [
                {
                    "meetingDay": 3,
                    "meetingStartTime": "16:00",
                    "meetingEndTime": "17:00",
                    "meetingScheduleId": "158854",
                    "assignedRoom1": null,
                    "assignedRoom2": ""
                }
            ],
            "meetingId": "101942",
            "sectionNumber": "0501",
            "subtitle": "",
            "cancel": "",
            "waitlist": "N",
            "online": "",
            "enrollmentCapacity": "20",
            "actualEnrolment": "0",
            "actualWaitlist": "0",
            "enrollmentIndicator": null,
            "meetingStatusNotes": null,
            "enrollmentControls": []
        },
        {
            "meetingName": "TUT0601",
            "meetingType": "TUT",
            "instructors": [],
            "detail": [
                {
                    "meetingDay": 4,
                    "meetingStartTime": "11:00",
                    "meetingEndTime": "12:00",
                    "meetingScheduleId": "171062",
                    "assignedRoom1": null,
                    "assignedRoom2": ""
                }
            ],
            "meetingId": "101944",
            "sectionNumber": "0601",
            "subtitle": "",
            "cancel": "",
            "waitlist": "N",
            "online": "",
            "enrollmentCapacity": "20",
            "actualEnrolment": "0",
            "actualWaitlist": "0",
            "enrollmentIndicator": null,
            "meetingStatusNotes": "",
            "enrollmentControls": []
        },
        {
            "meetingName": "TUT0701",
            "meetingType": "TUT",
            "instructors": [],
            "detail": [
                {
                    "meetingDay": 4,
                    "meetingStartTime": "12:00",
                    "meetingEndTime": "13:00",
                    "meetingScheduleId": "171063",
                    "assignedRoom1": null,
                    "assignedRoom2": ""
                }
            ],
            "meetingId": "101945",
            "sectionNumber": "0701",
            "subtitle": "",
            "cancel": "",
            "waitlist": "N",
            "online": "",
            "enrollmentCapacity": "20",
            "actualEnrolment": "0",
            "actualWaitlist": "0",
            "enrollmentIndicator": null,
            "meetingStatusNotes": "",
            "enrollmentControls": []
        },
        {
            "meetingName": "TUT5101",
            "meetingType": "TUT",
            "instructors": [],
            "detail": [
                {
                    "meetingDay": 3,
                    "meetingStartTime": "17:00",
                    "meetingEndTime": "18:00",
                    "meetingScheduleId": "171061",
                    "assignedRoom1": null,
                    "assignedRoom2": ""
                }
            ],
            "meetingId": "101943",
            "sectionNumber": "5101",
            "subtitle": "",
            "cancel": "",
            "waitlist": "N",
            "online": "",
            "enrollmentCapacity": "20",
            "actualEnrolment": "0",
            "actualWaitlist": "0",
            "enrollmentIndicator": null,
            "meetingStatusNotes": "",
            "enrollmentControls": []
        },
        {
            "meetingName": "TUT5201",
            "meetingType": "TUT",
            "instructors": [],
            "detail": [
                {
                    "meetingDay": 4,
                    "meetingStartTime": "18:00",
                    "meetingEndTime": "19:00",
                    "meetingScheduleId": "171060",
                    "assignedRoom1": null,
                    "assignedRoom2": ""
                }
            ],
            "meetingId": "101946",
            "sectionNumber": "5201",
            "subtitle": "",
            "cancel": "",
            "waitlist": "N",
            "online": "",
            "enrollmentCapacity": "20",
            "actualEnrolment": "0",
            "actualWaitlist": "0",
            "enrollmentIndicator": null,
            "meetingStatusNotes": "",
            "enrollmentControls": []
        },
        {
            "meetingName": "TUT5301",
            "meetingType": "TUT",
            "instructors": [],
            "detail": [
                {
                    "meetingDay": 4,
                    "meetingStartTime": "19:00",
                    "meetingEndTime": "20:00",
                    "meetingScheduleId": "171059",
                    "assignedRoom1": null,
                    "assignedRoom2": ""
                }
            ],
            "meetingId": "101947",
            "sectionNumber": "5301",
            "subtitle": "",
            "cancel": "",
            "waitlist": "N",
            "online": "",
            "enrollmentCapacity": "20",
            "actualEnrolment": "0",
            "actualWaitlist": "0",
            "enrollmentIndicator": null,
            "meetingStatusNotes": "",
            "enrollmentControls": []
        }
    ],
    "courseId": "33319",
    "org": "PSY",
    "orgName": "Psychology (PSY) (JLP)",
    "courseTitle": "Statistics II",
    "code": "PSY202H1",
    "courseDescription": "Fundamentals of statistical analysis of experimental and observational data including linear models, the analysis of variance, a priori contrasts, post-hoc tests, power analysis and effect size calculations.",
    "prerequisite": "PSY201H1 (or exclusion)",
    "corequisite": "",
    "exclusion": "ECO220Y1/ECO227Y1/STA221H1/SOC252H1/SOC300H1",
    "recommendedPreparation": "",
    "section": "S",
    "session": "20199",
    "webTimetableInstructions": "",
    "breadthCategories": "The Physical and Mathematical Universes (5)",
    "distributionCategories": "Science"
}